MANIFEST.in
setup.py
approx_count/__init__.py
approx_count/admin.py
approx_count/mixin.py
django_admin_approx_count.egg-info/PKG-INFO
django_admin_approx_count.egg-info/SOURCES.txt
django_admin_approx_count.egg-info/dependency_links.txt
django_admin_approx_count.egg-info/requires.txt
django_admin_approx_count.egg-info/top_level.txt
django_admin_approx_count.egg-info/zip-safe