Metadata-Version: 1.1
Name: django-admin-approx-count
Version: 0.1.2
Summary: A dirty mixin to rescue from dumb count(*) query of Django admin
Home-page: http://github.com/lqez/django-admin-approx-count
Author: Park Hyunwoo
Author-email: ez.amiryo@gmail.com
License: UNKNOWN
Platform: UNKNOWN
Classifier: Development Status :: 4 - Beta
Classifier: Environment :: Web Environment
Classifier: Framework :: Django
Classifier: Intended Audience :: Developers
Classifier: License :: OSI Approved :: MIT License
Classifier: Programming Language :: Python :: 2.7
Classifier: Programming Language :: Python
Classifier: Topic :: Internet :: WWW/HTTP
Classifier: Topic :: Software Development :: Libraries :: Python Modules
Classifier: Topic :: Utilities
